{"resultCount":[2736950],"facets":{"author_facet":[{"value":"Ferreira, Isabel C.F.R.","translated":"Ferreira, Isabel C.F.R.","count":1974,"href":"?limit=0&type=AllFields&filter%5B%5D=author_facet%3A%22Ferreira%2C+Isabel+C.F.R.%22"},{"value":"Reis, R. L.","translated":"Reis, R. L.","count":1545,"href":"?limit=0&type=AllFields&filter%5B%5D=author_facet%3A%22Reis%2C+R.+L.%22"},{"value":"Barros, Lillian","translated":"Barros, Lillian","count":1430,"href":"?limit=0&type=AllFields&filter%5B%5D=author_facet%3A%22Barros%2C+Lillian%22"},{"value":"Teixeira, J. A.","translated":"Teixeira, J. A.","count":1400,"href":"?limit=0&type=AllFields&filter%5B%5D=author_facet%3A%22Teixeira%2C+J.+A.%22"},{"value":"Sirunyan, A. M.","translated":"Sirunyan, A. M.","count":1187,"href":"?limit=0&type=AllFields&filter%5B%5D=author_facet%3A%22Sirunyan%2C+A.+M.%22"},{"value":"Instituto de Engenharia Nuclear","translated":"Instituto de Engenharia Nuclear","count":1102,"href":"?limit=0&type=AllFields&filter%5B%5D=author_facet%3A%22Instituto+de+Engenharia+Nuclear%22"},{"value":"Castro, Nuno Filipe","translated":"Castro, Nuno Filipe","count":1097,"href":"?limit=0&type=AllFields&filter%5B%5D=author_facet%3A%22Castro%2C+Nuno+Filipe%22"},{"value":"Costa, M.","translated":"Costa, M.","count":999,"href":"?limit=0&type=AllFields&filter%5B%5D=author_facet%3A%22Costa%2C+M.%22"},{"value":"Onofre, A.","translated":"Onofre, A.","count":997,"href":"?limit=0&type=AllFields&filter%5B%5D=author_facet%3A%22Onofre%2C+A.%22"},{"value":"Adams, T.","translated":"Adams, T.","count":983,"href":"?limit=0&type=AllFields&filter%5B%5D=author_facet%3A%22Adams%2C+T.%22"},{"value":"Castro, A.","translated":"Castro, A.","count":975,"href":"?limit=0&type=AllFields&filter%5B%5D=author_facet%3A%22Castro%2C+A.%22"},{"value":"Lourenço, Paulo B.","translated":"Lourenço, Paulo B.","count":974,"href":"?limit=0&type=AllFields&filter%5B%5D=author_facet%3A%22Louren%C3%A7o%2C+Paulo+B.%22"},{"value":"ATLAS Collaboration","translated":"ATLAS Collaboration","count":971,"href":"?limit=0&type=AllFields&filter%5B%5D=author_facet%3A%22ATLAS+Collaboration%22"},{"value":"Stone, R.","translated":"Stone, R.","count":952,"href":"?limit=0&type=AllFields&filter%5B%5D=author_facet%3A%22Stone%2C+R.%22"},{"value":"Varela, J.","translated":"Varela, J.","count":950,"href":"?limit=0&type=AllFields&filter%5B%5D=author_facet%3A%22Varela%2C+J.%22"},{"value":"Banerjee, S.","translated":"Banerjee, S.","count":949,"href":"?limit=0&type=AllFields&filter%5B%5D=author_facet%3A%22Banerjee%2C+S.%22"},{"value":"Malik, S.","translated":"Malik, S.","count":949,"href":"?limit=0&type=AllFields&filter%5B%5D=author_facet%3A%22Malik%2C+S.%22"},{"value":"Gill, K.","translated":"Gill, K.","count":948,"href":"?limit=0&type=AllFields&filter%5B%5D=author_facet%3A%22Gill%2C+K.%22"},{"value":"Mitselmakher, G.","translated":"Mitselmakher, G.","count":948,"href":"?limit=0&type=AllFields&filter%5B%5D=author_facet%3A%22Mitselmakher%2C+G.%22"},{"value":"Bloom, K.","translated":"Bloom, K.","count":947,"href":"?limit=0&type=AllFields&filter%5B%5D=author_facet%3A%22Bloom%2C+K.%22"},{"value":"Choi, S.","translated":"Choi, S.","count":947,"href":"?limit=0&type=AllFields&filter%5B%5D=author_facet%3A%22Choi%2C+S.%22"},{"value":"Harder, K.","translated":"Harder, K.","count":947,"href":"?limit=0&type=AllFields&filter%5B%5D=author_facet%3A%22Harder%2C+K.%22"},{"value":"Hirosky, R.","translated":"Hirosky, R.","count":947,"href":"?limit=0&type=AllFields&filter%5B%5D=author_facet%3A%22Hirosky%2C+R.%22"},{"value":"Weber, M.","translated":"Weber, M.","count":947,"href":"?limit=0&type=AllFields&filter%5B%5D=author_facet%3A%22Weber%2C+M.%22"},{"value":"Askew, A.","translated":"Askew, A.","count":946,"href":"?limit=0&type=AllFields&filter%5B%5D=author_facet%3A%22Askew%2C+A.%22"},{"value":"Dominguez, A.","translated":"Dominguez, A.","count":946,"href":"?limit=0&type=AllFields&filter%5B%5D=author_facet%3A%22Dominguez%2C+A.%22"},{"value":"Gershtein, Y.","translated":"Gershtein, Y.","count":946,"href":"?limit=0&type=AllFields&filter%5B%5D=author_facet%3A%22Gershtein%2C+Y.%22"},{"value":"Meyer, A.","translated":"Meyer, A.","count":946,"href":"?limit=0&type=AllFields&filter%5B%5D=author_facet%3A%22Meyer%2C+A.%22"},{"value":"Narain, M.","translated":"Narain, M.","count":946,"href":"?limit=0&type=AllFields&filter%5B%5D=author_facet%3A%22Narain%2C+M.%22"},{"value":"Parashar, N.","translated":"Parashar, N.","count":946,"href":"?limit=0&type=AllFields&filter%5B%5D=author_facet%3A%22Parashar%2C+N.%22"}],"dc.subject.por.fl_str_mv":[{"value":"Educação","translated":"Educação","count":19009,"href":"?limit=0&type=AllFields&filter%5B%5D=dc.subject.por.fl_str_mv%3A%22Educa%C3%A7%C3%A3o%22"},{"value":"Enfermagem","translated":"Enfermagem","count":11174,"href":"?limit=0&type=AllFields&filter%5B%5D=dc.subject.por.fl_str_mv%3A%22Enfermagem%22"},{"value":"Brasil","translated":"Brasil","count":10701,"href":"?limit=0&type=AllFields&filter%5B%5D=dc.subject.por.fl_str_mv%3A%22Brasil%22"},{"value":"Teses","translated":"Teses","count":9987,"href":"?limit=0&type=AllFields&filter%5B%5D=dc.subject.por.fl_str_mv%3A%22Teses%22"},{"value":"Psicologia","translated":"Psicologia","count":9629,"href":"?limit=0&type=AllFields&filter%5B%5D=dc.subject.por.fl_str_mv%3A%22Psicologia%22"},{"value":"Medicina","translated":"Medicina","count":9599,"href":"?limit=0&type=AllFields&filter%5B%5D=dc.subject.por.fl_str_mv%3A%22Medicina%22"},{"value":"Portugal","translated":"Portugal","count":7829,"href":"?limit=0&type=AllFields&filter%5B%5D=dc.subject.por.fl_str_mv%3A%22Portugal%22"},{"value":"Direito","translated":"Direito","count":7041,"href":"?limit=0&type=AllFields&filter%5B%5D=dc.subject.por.fl_str_mv%3A%22Direito%22"},{"value":"Sustentabilidade","translated":"Sustentabilidade","count":6827,"href":"?limit=0&type=AllFields&filter%5B%5D=dc.subject.por.fl_str_mv%3A%22Sustentabilidade%22"},{"value":"Criança","translated":"Criança","count":6629,"href":"?limit=0&type=AllFields&filter%5B%5D=dc.subject.por.fl_str_mv%3A%22Crian%C3%A7a%22"},{"value":"Aprendizagem","translated":"Aprendizagem","count":6457,"href":"?limit=0&type=AllFields&filter%5B%5D=dc.subject.por.fl_str_mv%3A%22Aprendizagem%22"},{"value":"História","translated":"História","count":6401,"href":"?limit=0&type=AllFields&filter%5B%5D=dc.subject.por.fl_str_mv%3A%22Hist%C3%B3ria%22"},{"value":"Comunicação","translated":"Comunicação","count":6280,"href":"?limit=0&type=AllFields&filter%5B%5D=dc.subject.por.fl_str_mv%3A%22Comunica%C3%A7%C3%A3o%22"},{"value":"Políticas públicas","translated":"Políticas públicas","count":6124,"href":"?limit=0&type=AllFields&filter%5B%5D=dc.subject.por.fl_str_mv%3A%22Pol%C3%ADticas+p%C3%BAblicas%22"},{"value":"Psychology","translated":"Psychology","count":6107,"href":"?limit=0&type=AllFields&filter%5B%5D=dc.subject.por.fl_str_mv%3A%22Psychology%22"},{"value":"Qualidade de vida","translated":"Qualidade de vida","count":6089,"href":"?limit=0&type=AllFields&filter%5B%5D=dc.subject.por.fl_str_mv%3A%22Qualidade+de+vida%22"},{"value":"Ensino","translated":"Ensino","count":6066,"href":"?limit=0&type=AllFields&filter%5B%5D=dc.subject.por.fl_str_mv%3A%22Ensino%22"},{"value":"Formação de professores","translated":"Formação de professores","count":5666,"href":"?limit=0&type=AllFields&filter%5B%5D=dc.subject.por.fl_str_mv%3A%22Forma%C3%A7%C3%A3o+de+professores%22"},{"value":"Idoso","translated":"Idoso","count":5350,"href":"?limit=0&type=AllFields&filter%5B%5D=dc.subject.por.fl_str_mv%3A%22Idoso%22"},{"value":"Ciências da saúde","translated":"Ciências da saúde","count":5340,"href":"?limit=0&type=AllFields&filter%5B%5D=dc.subject.por.fl_str_mv%3A%22Ci%C3%AAncias+da+sa%C3%BAde%22"},{"value":"Brazil","translated":"Brazil","count":5235,"href":"?limit=0&type=AllFields&filter%5B%5D=dc.subject.por.fl_str_mv%3A%22Brazil%22"},{"value":"Health sciences","translated":"Health sciences","count":5112,"href":"?limit=0&type=AllFields&filter%5B%5D=dc.subject.por.fl_str_mv%3A%22Health+sciences%22"},{"value":"Memória","translated":"Memória","count":4835,"href":"?limit=0&type=AllFields&filter%5B%5D=dc.subject.por.fl_str_mv%3A%22Mem%C3%B3ria%22"},{"value":"Família","translated":"Família","count":4792,"href":"?limit=0&type=AllFields&filter%5B%5D=dc.subject.por.fl_str_mv%3A%22Fam%C3%ADlia%22"},{"value":"Cultura","translated":"Cultura","count":4772,"href":"?limit=0&type=AllFields&filter%5B%5D=dc.subject.por.fl_str_mv%3A%22Cultura%22"},{"value":"Engenharia civil","translated":"Engenharia civil","count":4578,"href":"?limit=0&type=AllFields&filter%5B%5D=dc.subject.por.fl_str_mv%3A%22Engenharia+civil%22"},{"value":"Gênero","translated":"Gênero","count":4556,"href":"?limit=0&type=AllFields&filter%5B%5D=dc.subject.por.fl_str_mv%3A%22G%C3%AAnero%22"},{"value":"Trabalho","translated":"Trabalho","count":4540,"href":"?limit=0&type=AllFields&filter%5B%5D=dc.subject.por.fl_str_mv%3A%22Trabalho%22"},{"value":"Saúde","translated":"Saúde","count":4398,"href":"?limit=0&type=AllFields&filter%5B%5D=dc.subject.por.fl_str_mv%3A%22Sa%C3%BAde%22"},{"value":"Engenharia mecânica","translated":"Engenharia mecânica","count":4340,"href":"?limit=0&type=AllFields&filter%5B%5D=dc.subject.por.fl_str_mv%3A%22Engenharia+mec%C3%A2nica%22"}],"eu_rights_str_mv":[{"value":"openAccess","translated":"openAccess","count":2729112,"href":"?limit=0&type=AllFields&filter%5B%5D=eu_rights_str_mv%3A%22openAccess%22"},{"value":"embargoedAccess","translated":"embargoedAccess","count":7469,"href":"?limit=0&type=AllFields&filter%5B%5D=eu_rights_str_mv%3A%22embargoedAccess%22"},{"value":"restrictedAccess","translated":"restrictedAccess","count":3,"href":"?limit=0&type=AllFields&filter%5B%5D=eu_rights_str_mv%3A%22restrictedAccess%22"}],"dc.publisher.program.fl_str_mv":[{"value":"Programa de Pós-Graduação em Educação","translated":"Programa de Pós-Graduação em Educação","count":5859,"href":"?limit=0&type=AllFields&filter%5B%5D=dc.publisher.program.fl_str_mv%3A%22Programa+de+P%C3%B3s-Gradua%C3%A7%C3%A3o+em+Educa%C3%A7%C3%A3o%22"},{"value":"Engenharia Elétrica","translated":"Engenharia Elétrica","count":3780,"href":"?limit=0&type=AllFields&filter%5B%5D=dc.publisher.program.fl_str_mv%3A%22Engenharia+El%C3%A9trica%22"},{"value":"Engenharia Mecânica","translated":"Engenharia Mecânica","count":3241,"href":"?limit=0&type=AllFields&filter%5B%5D=dc.publisher.program.fl_str_mv%3A%22Engenharia+Mec%C3%A2nica%22"},{"value":"Física","translated":"Física","count":3199,"href":"?limit=0&type=AllFields&filter%5B%5D=dc.publisher.program.fl_str_mv%3A%22F%C3%ADsica%22"},{"value":"Programa de Pós-Graduação em Letras","translated":"Programa de Pós-Graduação em Letras","count":2822,"href":"?limit=0&type=AllFields&filter%5B%5D=dc.publisher.program.fl_str_mv%3A%22Programa+de+P%C3%B3s-Gradua%C3%A7%C3%A3o+em+Letras%22"},{"value":"Programa de Estudos Pós-Graduados em Direito","translated":"Programa de Estudos Pós-Graduados em Direito","count":2805,"href":"?limit=0&type=AllFields&filter%5B%5D=dc.publisher.program.fl_str_mv%3A%22Programa+de+Estudos+P%C3%B3s-Graduados+em+Direito%22"},{"value":"Engenharia Civil","translated":"Engenharia Civil","count":2633,"href":"?limit=0&type=AllFields&filter%5B%5D=dc.publisher.program.fl_str_mv%3A%22Engenharia+Civil%22"},{"value":"Programa de Pós-Graduação em Engenharia Elétrica","translated":"Programa de Pós-Graduação em Engenharia Elétrica","count":2527,"href":"?limit=0&type=AllFields&filter%5B%5D=dc.publisher.program.fl_str_mv%3A%22Programa+de+P%C3%B3s-Gradua%C3%A7%C3%A3o+em+Engenharia+El%C3%A9trica%22"},{"value":"Programa de Pós-Graduação em Engenharia Civil","translated":"Programa de Pós-Graduação em Engenharia Civil","count":2501,"href":"?limit=0&type=AllFields&filter%5B%5D=dc.publisher.program.fl_str_mv%3A%22Programa+de+P%C3%B3s-Gradua%C3%A7%C3%A3o+em+Engenharia+Civil%22"},{"value":"Arquitetura e Urbanismo","translated":"Arquitetura e Urbanismo","count":2460,"href":"?limit=0&type=AllFields&filter%5B%5D=dc.publisher.program.fl_str_mv%3A%22Arquitetura+e+Urbanismo%22"},{"value":"Educação","translated":"Educação","count":2450,"href":"?limit=0&type=AllFields&filter%5B%5D=dc.publisher.program.fl_str_mv%3A%22Educa%C3%A7%C3%A3o%22"},{"value":"Química","translated":"Química","count":2410,"href":"?limit=0&type=AllFields&filter%5B%5D=dc.publisher.program.fl_str_mv%3A%22Qu%C3%ADmica%22"},{"value":"Programa de Pós-Graduação em Direito","translated":"Programa de Pós-Graduação em Direito","count":2192,"href":"?limit=0&type=AllFields&filter%5B%5D=dc.publisher.program.fl_str_mv%3A%22Programa+de+P%C3%B3s-Gradua%C3%A7%C3%A3o+em+Direito%22"},{"value":"Engenharia de Produção","translated":"Engenharia de Produção","count":2038,"href":"?limit=0&type=AllFields&filter%5B%5D=dc.publisher.program.fl_str_mv%3A%22Engenharia+de+Produ%C3%A7%C3%A3o%22"},{"value":"Programa de Pós-Graduação em Agronomia","translated":"Programa de Pós-Graduação em Agronomia","count":2028,"href":"?limit=0&type=AllFields&filter%5B%5D=dc.publisher.program.fl_str_mv%3A%22Programa+de+P%C3%B3s-Gradua%C3%A7%C3%A3o+em+Agronomia%22"},{"value":"Programa de Pós-Graduação em História","translated":"Programa de Pós-Graduação em História","count":1874,"href":"?limit=0&type=AllFields&filter%5B%5D=dc.publisher.program.fl_str_mv%3A%22Programa+de+P%C3%B3s-Gradua%C3%A7%C3%A3o+em+Hist%C3%B3ria%22"},{"value":"Ciências da Computação e Matemática Computacional","translated":"Ciências da Computação e Matemática Computacional","count":1743,"href":"?limit=0&type=AllFields&filter%5B%5D=dc.publisher.program.fl_str_mv%3A%22Ci%C3%AAncias+da+Computa%C3%A7%C3%A3o+e+Matem%C3%A1tica+Computacional%22"},{"value":"Programa de Pós-Graduação em Engenharia de Produção","translated":"Programa de Pós-Graduação em Engenharia de Produção","count":1732,"href":"?limit=0&type=AllFields&filter%5B%5D=dc.publisher.program.fl_str_mv%3A%22Programa+de+P%C3%B3s-Gradua%C3%A7%C3%A3o+em+Engenharia+de+Produ%C3%A7%C3%A3o%22"},{"value":"Direito","translated":"Direito","count":1722,"href":"?limit=0&type=AllFields&filter%5B%5D=dc.publisher.program.fl_str_mv%3A%22Direito%22"},{"value":"Tecnologia Nuclear","translated":"Tecnologia Nuclear","count":1710,"href":"?limit=0&type=AllFields&filter%5B%5D=dc.publisher.program.fl_str_mv%3A%22Tecnologia+Nuclear%22"},{"value":"Programa de Pós-Graduação em Química","translated":"Programa de Pós-Graduação em Química","count":1654,"href":"?limit=0&type=AllFields&filter%5B%5D=dc.publisher.program.fl_str_mv%3A%22Programa+de+P%C3%B3s-Gradua%C3%A7%C3%A3o+em+Qu%C3%ADmica%22"},{"value":"Saúde Pública","translated":"Saúde Pública","count":1637,"href":"?limit=0&type=AllFields&filter%5B%5D=dc.publisher.program.fl_str_mv%3A%22Sa%C3%BAde+P%C3%BAblica%22"},{"value":"Programa de Pós-Graduação em Saúde Coletiva","translated":"Programa de Pós-Graduação em Saúde Coletiva","count":1631,"href":"?limit=0&type=AllFields&filter%5B%5D=dc.publisher.program.fl_str_mv%3A%22Programa+de+P%C3%B3s-Gradua%C3%A7%C3%A3o+em+Sa%C3%BAde+Coletiva%22"},{"value":"Programa de Pós-graduação em Educação","translated":"Programa de Pós-graduação em Educação","count":1572,"href":"?limit=0&type=AllFields&filter%5B%5D=dc.publisher.program.fl_str_mv%3A%22Programa+de+P%C3%B3s-gradua%C3%A7%C3%A3o+em+Educa%C3%A7%C3%A3o%22"},{"value":"Programa de Pós-Graduação em Administração","translated":"Programa de Pós-Graduação em Administração","count":1569,"href":"?limit=0&type=AllFields&filter%5B%5D=dc.publisher.program.fl_str_mv%3A%22Programa+de+P%C3%B3s-Gradua%C3%A7%C3%A3o+em+Administra%C3%A7%C3%A3o%22"},{"value":"Programa de Pós-Graduação em Ciências Sociais","translated":"Programa de Pós-Graduação em Ciências Sociais","count":1448,"href":"?limit=0&type=AllFields&filter%5B%5D=dc.publisher.program.fl_str_mv%3A%22Programa+de+P%C3%B3s-Gradua%C3%A7%C3%A3o+em+Ci%C3%AAncias+Sociais%22"},{"value":"Administração","translated":"Administração","count":1388,"href":"?limit=0&type=AllFields&filter%5B%5D=dc.publisher.program.fl_str_mv%3A%22Administra%C3%A7%C3%A3o%22"},{"value":"Programa de Pós-Graduação em Zootecnia","translated":"Programa de Pós-Graduação em Zootecnia","count":1383,"href":"?limit=0&type=AllFields&filter%5B%5D=dc.publisher.program.fl_str_mv%3A%22Programa+de+P%C3%B3s-Gradua%C3%A7%C3%A3o+em+Zootecnia%22"},{"value":"Programa de Pós-Graduação em Enfermagem","translated":"Programa de Pós-Graduação em Enfermagem","count":1330,"href":"?limit=0&type=AllFields&filter%5B%5D=dc.publisher.program.fl_str_mv%3A%22Programa+de+P%C3%B3s-Gradua%C3%A7%C3%A3o+em+Enfermagem%22"},{"value":"Programa de Pós-Graduação em Geografia","translated":"Programa de Pós-Graduação em Geografia","count":1278,"href":"?limit=0&type=AllFields&filter%5B%5D=dc.publisher.program.fl_str_mv%3A%22Programa+de+P%C3%B3s-Gradua%C3%A7%C3%A3o+em+Geografia%22"}],"dc.subject.cnpq.fl_str_mv":[{"value":"CNPQ::CIENCIAS HUMANAS::EDUCACAO","translated":"CNPQ::CIENCIAS HUMANAS::EDUCACAO","count":13758,"href":"?limit=0&type=AllFields&filter%5B%5D=dc.subject.cnpq.fl_str_mv%3A%22CNPQ%3A%3ACIENCIAS+HUMANAS%3A%3AEDUCACAO%22"},{"value":"CNPQ::CIENCIAS SOCIAIS APLICADAS::DIREITO","translated":"CNPQ::CIENCIAS SOCIAIS APLICADAS::DIREITO","count":8222,"href":"?limit=0&type=AllFields&filter%5B%5D=dc.subject.cnpq.fl_str_mv%3A%22CNPQ%3A%3ACIENCIAS+SOCIAIS+APLICADAS%3A%3ADIREITO%22"},{"value":"CNPQ::ENGENHARIAS","translated":"CNPQ::ENGENHARIAS","count":5301,"href":"?limit=0&type=AllFields&filter%5B%5D=dc.subject.cnpq.fl_str_mv%3A%22CNPQ%3A%3AENGENHARIAS%22"},{"value":"CNPQ::ENGENHARIAS::ENGENHARIA ELETRICA","translated":"CNPQ::ENGENHARIAS::ENGENHARIA ELETRICA","count":4664,"href":"?limit=0&type=AllFields&filter%5B%5D=dc.subject.cnpq.fl_str_mv%3A%22CNPQ%3A%3AENGENHARIAS%3A%3AENGENHARIA+ELETRICA%22"},{"value":"CNPQ::CIENCIAS HUMANAS::PSICOLOGIA","translated":"CNPQ::CIENCIAS HUMANAS::PSICOLOGIA","count":4637,"href":"?limit=0&type=AllFields&filter%5B%5D=dc.subject.cnpq.fl_str_mv%3A%22CNPQ%3A%3ACIENCIAS+HUMANAS%3A%3APSICOLOGIA%22"},{"value":"CNPQ::CIENCIAS SOCIAIS APLICADAS","translated":"CNPQ::CIENCIAS SOCIAIS APLICADAS","count":4445,"href":"?limit=0&type=AllFields&filter%5B%5D=dc.subject.cnpq.fl_str_mv%3A%22CNPQ%3A%3ACIENCIAS+SOCIAIS+APLICADAS%22"},{"value":"CNPQ::ENGENHARIAS::ENGENHARIA DE PRODUCAO","translated":"CNPQ::ENGENHARIAS::ENGENHARIA DE PRODUCAO","count":4318,"href":"?limit=0&type=AllFields&filter%5B%5D=dc.subject.cnpq.fl_str_mv%3A%22CNPQ%3A%3AENGENHARIAS%3A%3AENGENHARIA+DE+PRODUCAO%22"},{"value":"CNPQ::CIENCIAS HUMANAS::HISTORIA","translated":"CNPQ::CIENCIAS HUMANAS::HISTORIA","count":4130,"href":"?limit=0&type=AllFields&filter%5B%5D=dc.subject.cnpq.fl_str_mv%3A%22CNPQ%3A%3ACIENCIAS+HUMANAS%3A%3AHISTORIA%22"},{"value":"Ciências biológicas","translated":"Ciências biológicas","count":4122,"href":"?limit=0&type=AllFields&filter%5B%5D=dc.subject.cnpq.fl_str_mv%3A%22Ci%C3%AAncias+biol%C3%B3gicas%22"},{"value":"CNPQ::CIENCIAS EXATAS E DA TERRA::CIENCIA DA COMPUTACAO","translated":"CNPQ::CIENCIAS EXATAS E DA TERRA::CIENCIA DA COMPUTACAO","count":4065,"href":"?limit=0&type=AllFields&filter%5B%5D=dc.subject.cnpq.fl_str_mv%3A%22CNPQ%3A%3ACIENCIAS+EXATAS+E+DA+TERRA%3A%3ACIENCIA+DA+COMPUTACAO%22"},{"value":"CNPQ::CIENCIAS SOCIAIS APLICADAS::ADMINISTRACAO","translated":"CNPQ::CIENCIAS SOCIAIS APLICADAS::ADMINISTRACAO","count":4025,"href":"?limit=0&type=AllFields&filter%5B%5D=dc.subject.cnpq.fl_str_mv%3A%22CNPQ%3A%3ACIENCIAS+SOCIAIS+APLICADAS%3A%3AADMINISTRACAO%22"},{"value":"CNPQ::CIENCIAS AGRARIAS::AGRONOMIA","translated":"CNPQ::CIENCIAS AGRARIAS::AGRONOMIA","count":3927,"href":"?limit=0&type=AllFields&filter%5B%5D=dc.subject.cnpq.fl_str_mv%3A%22CNPQ%3A%3ACIENCIAS+AGRARIAS%3A%3AAGRONOMIA%22"},{"value":"CIENCIAS HUMANAS::EDUCACAO","translated":"CIENCIAS HUMANAS::EDUCACAO","count":3912,"href":"?limit=0&type=AllFields&filter%5B%5D=dc.subject.cnpq.fl_str_mv%3A%22CIENCIAS+HUMANAS%3A%3AEDUCACAO%22"},{"value":"CNPQ::CIENCIAS DA SAUDE","translated":"CNPQ::CIENCIAS DA SAUDE","count":3720,"href":"?limit=0&type=AllFields&filter%5B%5D=dc.subject.cnpq.fl_str_mv%3A%22CNPQ%3A%3ACIENCIAS+DA+SAUDE%22"},{"value":"Ciências exatas e da terra","translated":"Ciências exatas e da terra","count":3522,"href":"?limit=0&type=AllFields&filter%5B%5D=dc.subject.cnpq.fl_str_mv%3A%22Ci%C3%AAncias+exatas+e+da+terra%22"},{"value":"CNPQ::CIENCIAS SOCIAIS APLICADAS::COMUNICACAO","translated":"CNPQ::CIENCIAS SOCIAIS APLICADAS::COMUNICACAO","count":3502,"href":"?limit=0&type=AllFields&filter%5B%5D=dc.subject.cnpq.fl_str_mv%3A%22CNPQ%3A%3ACIENCIAS+SOCIAIS+APLICADAS%3A%3ACOMUNICACAO%22"},{"value":"CNPQ::CIENCIAS EXATAS E DA TERRA::QUIMICA","translated":"CNPQ::CIENCIAS EXATAS E DA TERRA::QUIMICA","count":3474,"href":"?limit=0&type=AllFields&filter%5B%5D=dc.subject.cnpq.fl_str_mv%3A%22CNPQ%3A%3ACIENCIAS+EXATAS+E+DA+TERRA%3A%3AQUIMICA%22"},{"value":"CNPQ::CIENCIAS HUMANAS","translated":"CNPQ::CIENCIAS HUMANAS","count":3385,"href":"?limit=0&type=AllFields&filter%5B%5D=dc.subject.cnpq.fl_str_mv%3A%22CNPQ%3A%3ACIENCIAS+HUMANAS%22"},{"value":"CNPQ::LINGUISTICA, LETRAS E ARTES::LETRAS","translated":"CNPQ::LINGUISTICA, LETRAS E ARTES::LETRAS","count":3236,"href":"?limit=0&type=AllFields&filter%5B%5D=dc.subject.cnpq.fl_str_mv%3A%22CNPQ%3A%3ALINGUISTICA%2C+LETRAS+E+ARTES%3A%3ALETRAS%22"},{"value":"CNPQ::CIENCIAS BIOLOGICAS","translated":"CNPQ::CIENCIAS BIOLOGICAS","count":3185,"href":"?limit=0&type=AllFields&filter%5B%5D=dc.subject.cnpq.fl_str_mv%3A%22CNPQ%3A%3ACIENCIAS+BIOLOGICAS%22"},{"value":"CNPQ::ENGENHARIAS::ENGENHARIA CIVIL","translated":"CNPQ::ENGENHARIAS::ENGENHARIA CIVIL","count":2982,"href":"?limit=0&type=AllFields&filter%5B%5D=dc.subject.cnpq.fl_str_mv%3A%22CNPQ%3A%3AENGENHARIAS%3A%3AENGENHARIA+CIVIL%22"},{"value":"CNPQ::ENGENHARIAS::ENGENHARIA MECANICA","translated":"CNPQ::ENGENHARIAS::ENGENHARIA MECANICA","count":2868,"href":"?limit=0&type=AllFields&filter%5B%5D=dc.subject.cnpq.fl_str_mv%3A%22CNPQ%3A%3AENGENHARIAS%3A%3AENGENHARIA+MECANICA%22"},{"value":"CNPQ::CIENCIAS EXATAS E DA TERRA::MATEMATICA","translated":"CNPQ::CIENCIAS EXATAS E DA TERRA::MATEMATICA","count":2697,"href":"?limit=0&type=AllFields&filter%5B%5D=dc.subject.cnpq.fl_str_mv%3A%22CNPQ%3A%3ACIENCIAS+EXATAS+E+DA+TERRA%3A%3AMATEMATICA%22"},{"value":"CNPQ::CIENCIAS SOCIAIS APLICADAS::ECONOMIA","translated":"CNPQ::CIENCIAS SOCIAIS APLICADAS::ECONOMIA","count":2565,"href":"?limit=0&type=AllFields&filter%5B%5D=dc.subject.cnpq.fl_str_mv%3A%22CNPQ%3A%3ACIENCIAS+SOCIAIS+APLICADAS%3A%3AECONOMIA%22"},{"value":"CNPQ::CIENCIAS EXATAS E DA TERRA","translated":"CNPQ::CIENCIAS EXATAS E DA TERRA","count":2504,"href":"?limit=0&type=AllFields&filter%5B%5D=dc.subject.cnpq.fl_str_mv%3A%22CNPQ%3A%3ACIENCIAS+EXATAS+E+DA+TERRA%22"},{"value":"Ciências agrárias","translated":"Ciências agrárias","count":2361,"href":"?limit=0&type=AllFields&filter%5B%5D=dc.subject.cnpq.fl_str_mv%3A%22Ci%C3%AAncias+agr%C3%A1rias%22"},{"value":"Engenharias","translated":"Engenharias","count":2317,"href":"?limit=0&type=AllFields&filter%5B%5D=dc.subject.cnpq.fl_str_mv%3A%22Engenharias%22"},{"value":"CNPQ::CIENCIAS HUMANAS::TEOLOGIA","translated":"CNPQ::CIENCIAS HUMANAS::TEOLOGIA","count":2274,"href":"?limit=0&type=AllFields&filter%5B%5D=dc.subject.cnpq.fl_str_mv%3A%22CNPQ%3A%3ACIENCIAS+HUMANAS%3A%3ATEOLOGIA%22"},{"value":"CNPQ::CIENCIAS AGRARIAS","translated":"CNPQ::CIENCIAS AGRARIAS","count":2200,"href":"?limit=0&type=AllFields&filter%5B%5D=dc.subject.cnpq.fl_str_mv%3A%22CNPQ%3A%3ACIENCIAS+AGRARIAS%22"},{"value":"CNPQ::CIENCIAS DA SAUDE::EDUCACAO FISICA","translated":"CNPQ::CIENCIAS DA SAUDE::EDUCACAO FISICA","count":2177,"href":"?limit=0&type=AllFields&filter%5B%5D=dc.subject.cnpq.fl_str_mv%3A%22CNPQ%3A%3ACIENCIAS+DA+SAUDE%3A%3AEDUCACAO+FISICA%22"}],"publishDate":[{"value":"2018","translated":"2018","count":213315,"href":"?limit=0&type=AllFields&filter%5B%5D=publishDate%3A%222018%22"},{"value":"2017","translated":"2017","count":210213,"href":"?limit=0&type=AllFields&filter%5B%5D=publishDate%3A%222017%22"},{"value":"2016","translated":"2016","count":200540,"href":"?limit=0&type=AllFields&filter%5B%5D=publishDate%3A%222016%22"},{"value":"2014","translated":"2014","count":197488,"href":"?limit=0&type=AllFields&filter%5B%5D=publishDate%3A%222014%22"},{"value":"2019","translated":"2019","count":191768,"href":"?limit=0&type=AllFields&filter%5B%5D=publishDate%3A%222019%22"},{"value":"2015","translated":"2015","count":191623,"href":"?limit=0&type=AllFields&filter%5B%5D=publishDate%3A%222015%22"},{"value":"2013","translated":"2013","count":180769,"href":"?limit=0&type=AllFields&filter%5B%5D=publishDate%3A%222013%22"},{"value":"2012","translated":"2012","count":157849,"href":"?limit=0&type=AllFields&filter%5B%5D=publishDate%3A%222012%22"},{"value":"2011","translated":"2011","count":138789,"href":"?limit=0&type=AllFields&filter%5B%5D=publishDate%3A%222011%22"},{"value":"2020","translated":"2020","count":128202,"href":"?limit=0&type=AllFields&filter%5B%5D=publishDate%3A%222020%22"},{"value":"2010","translated":"2010","count":118798,"href":"?limit=0&type=AllFields&filter%5B%5D=publishDate%3A%222010%22"},{"value":"2009","translated":"2009","count":104379,"href":"?limit=0&type=AllFields&filter%5B%5D=publishDate%3A%222009%22"},{"value":"2008","translated":"2008","count":92975,"href":"?limit=0&type=AllFields&filter%5B%5D=publishDate%3A%222008%22"},{"value":"2021","translated":"2021","count":86962,"href":"?limit=0&type=AllFields&filter%5B%5D=publishDate%3A%222021%22"},{"value":"2007","translated":"2007","count":78027,"href":"?limit=0&type=AllFields&filter%5B%5D=publishDate%3A%222007%22"},{"value":"2006","translated":"2006","count":65621,"href":"?limit=0&type=AllFields&filter%5B%5D=publishDate%3A%222006%22"},{"value":"2005","translated":"2005","count":54414,"href":"?limit=0&type=AllFields&filter%5B%5D=publishDate%3A%222005%22"},{"value":"2004","translated":"2004","count":45225,"href":"?limit=0&type=AllFields&filter%5B%5D=publishDate%3A%222004%22"},{"value":"2003","translated":"2003","count":39558,"href":"?limit=0&type=AllFields&filter%5B%5D=publishDate%3A%222003%22"},{"value":"2002","translated":"2002","count":32615,"href":"?limit=0&type=AllFields&filter%5B%5D=publishDate%3A%222002%22"},{"value":"2001","translated":"2001","count":28037,"href":"?limit=0&type=AllFields&filter%5B%5D=publishDate%3A%222001%22"},{"value":"2000","translated":"2000","count":23002,"href":"?limit=0&type=AllFields&filter%5B%5D=publishDate%3A%222000%22"},{"value":"1999","translated":"1999","count":19243,"href":"?limit=0&type=AllFields&filter%5B%5D=publishDate%3A%221999%22"},{"value":"1998","translated":"1998","count":15920,"href":"?limit=0&type=AllFields&filter%5B%5D=publishDate%3A%221998%22"},{"value":"1997","translated":"1997","count":12581,"href":"?limit=0&type=AllFields&filter%5B%5D=publishDate%3A%221997%22"},{"value":"1996","translated":"1996","count":9769,"href":"?limit=0&type=AllFields&filter%5B%5D=publishDate%3A%221996%22"},{"value":"1995","translated":"1995","count":9476,"href":"?limit=0&type=AllFields&filter%5B%5D=publishDate%3A%221995%22"},{"value":"1994","translated":"1994","count":7728,"href":"?limit=0&type=AllFields&filter%5B%5D=publishDate%3A%221994%22"},{"value":"1993","translated":"1993","count":6981,"href":"?limit=0&type=AllFields&filter%5B%5D=publishDate%3A%221993%22"},{"value":"1992","translated":"1992","count":6427,"href":"?limit=0&type=AllFields&filter%5B%5D=publishDate%3A%221992%22"}],"language":[{"value":"por","translated":"Português","count":2103915,"href":"?limit=0&type=AllFields&filter%5B%5D=language%3A%22por%22"},{"value":"eng","translated":"Inglês","count":523211,"href":"?limit=0&type=AllFields&filter%5B%5D=language%3A%22eng%22"},{"value":"spa","translated":"Espanhol","count":27710,"href":"?limit=0&type=AllFields&filter%5B%5D=language%3A%22spa%22"},{"value":"fra","translated":"Francês","count":5405,"href":"?limit=0&type=AllFields&filter%5B%5D=language%3A%22fra%22"},{"value":"ita","translated":"Italiano","count":755,"href":"?limit=0&type=AllFields&filter%5B%5D=language%3A%22ita%22"},{"value":"deu","translated":"Alemão","count":533,"href":"?limit=0&type=AllFields&filter%5B%5D=language%3A%22deu%22"},{"value":"mul","translated":"Multi-Idiomas","count":235,"href":"?limit=0&type=AllFields&filter%5B%5D=language%3A%22mul%22"},{"value":"und","translated":"Indeterminado","count":45,"href":"?limit=0&type=AllFields&filter%5B%5D=language%3A%22und%22"},{"value":"glg","translated":"Galego","count":42,"href":"?limit=0&type=AllFields&filter%5B%5D=language%3A%22glg%22"},{"value":"rus","translated":"Russo","count":33,"href":"?limit=0&type=AllFields&filter%5B%5D=language%3A%22rus%22"},{"value":"fre","translated":"Francês","count":28,"href":"?limit=0&type=AllFields&filter%5B%5D=language%3A%22fre%22"},{"value":"POR","translated":"Portugês","count":26,"href":"?limit=0&type=AllFields&filter%5B%5D=language%3A%22POR%22"},{"value":"esp","translated":"Espanhol","count":26,"href":"?limit=0&type=AllFields&filter%5B%5D=language%3A%22esp%22"},{"value":"000","translated":"Portugês","count":24,"href":"?limit=0&type=AllFields&filter%5B%5D=language%3A%22000%22"},{"value":"cat","translated":"Catalão","count":19,"href":"?limit=0&type=AllFields&filter%5B%5D=language%3A%22cat%22"},{"value":"pol","translated":"Polonês","count":13,"href":"?limit=0&type=AllFields&filter%5B%5D=language%3A%22pol%22"},{"value":"ger","translated":"Alemão","count":11,"href":"?limit=0&type=AllFields&filter%5B%5D=language%3A%22ger%22"},{"value":"cmn","translated":"Chinês","count":10,"href":"?limit=0&type=AllFields&filter%5B%5D=language%3A%22cmn%22"},{"value":"fas","translated":"Persa","count":10,"href":"?limit=0&type=AllFields&filter%5B%5D=language%3A%22fas%22"},{"value":"hun","translated":"Húngaro","count":10,"href":"?limit=0&type=AllFields&filter%5B%5D=language%3A%22hun%22"},{"value":"Por","translated":"Portugês","count":6,"href":"?limit=0&type=AllFields&filter%5B%5D=language%3A%22Por%22"},{"value":"grn","translated":"Guarani","count":5,"href":"?limit=0&type=AllFields&filter%5B%5D=language%3A%22grn%22"},{"value":"zho","translated":"Chinês","count":5,"href":"?limit=0&type=AllFields&filter%5B%5D=language%3A%22zho%22"},{"value":"bzs","translated":"Portugês","count":4,"href":"?limit=0&type=AllFields&filter%5B%5D=language%3A%22bzs%22"},{"value":"jpn","translated":"Japonês","count":4,"href":"?limit=0&type=AllFields&filter%5B%5D=language%3A%22jpn%22"},{"value":"oth","translated":"Romeno","count":4,"href":"?limit=0&type=AllFields&filter%5B%5D=language%3A%22oth%22"},{"value":"Eng","translated":"Inglês","count":3,"href":"?limit=0&type=AllFields&filter%5B%5D=language%3A%22Eng%22"},{"value":"ell","translated":"Grego, Moderno (1453-)","count":3,"href":"?limit=0&type=AllFields&filter%5B%5D=language%3A%22ell%22"},{"value":"nld","translated":"Holandês","count":3,"href":"?limit=0&type=AllFields&filter%5B%5D=language%3A%22nld%22"},{"value":"tur","translated":"Turco","count":3,"href":"?limit=0&type=AllFields&filter%5B%5D=language%3A%22tur%22"}],"format":[{"value":"article","translated":"Article","count":1190502,"href":"?limit=0&type=AllFields&filter%5B%5D=format%3A%22article%22"},{"value":"masterThesis","translated":"Master thesis","count":738440,"href":"?limit=0&type=AllFields&filter%5B%5D=format%3A%22masterThesis%22"},{"value":"doctoralThesis","translated":"Doctoral thesis","count":204025,"href":"?limit=0&type=AllFields&filter%5B%5D=format%3A%22doctoralThesis%22"},{"value":"bachelorThesis","translated":"Bachelor thesis","count":65276,"href":"?limit=0&type=AllFields&filter%5B%5D=format%3A%22bachelorThesis%22"},{"value":"report","translated":"Report","count":34853,"href":"?limit=0&type=AllFields&filter%5B%5D=format%3A%22report%22"},{"value":"bookPart","translated":"Book part","count":34723,"href":"?limit=0&type=AllFields&filter%5B%5D=format%3A%22bookPart%22"},{"value":"conferenceObject","translated":"Conference object","count":31926,"href":"?limit=0&type=AllFields&filter%5B%5D=format%3A%22conferenceObject%22"},{"value":"book","translated":"Book","count":30398,"href":"?limit=0&type=AllFields&filter%5B%5D=format%3A%22book%22"},{"value":"review","translated":"Review","count":5539,"href":"?limit=0&type=AllFields&filter%5B%5D=format%3A%22review%22"},{"value":"other","translated":"Other","count":1284,"href":"?limit=0&type=AllFields&filter%5B%5D=format%3A%22other%22"},{"value":"dataset","translated":"Dataset","count":310,"href":"?limit=0&type=AllFields&filter%5B%5D=format%3A%22dataset%22"},{"value":"workingPaper","translated":"Working paper","count":1,"href":"?limit=0&type=AllFields&filter%5B%5D=format%3A%22workingPaper%22"}],"institution":[{"value":"RCAAP","translated":"RCAAP","count":693246,"href":"?limit=0&type=AllFields&filter%5B%5D=institution%3A%22RCAAP%22"},{"value":"USP","translated":"USP","count":163233,"href":"?limit=0&type=AllFields&filter%5B%5D=institution%3A%22USP%22"},{"value":"UFRGS","translated":"UFRGS","count":149915,"href":"?limit=0&type=AllFields&filter%5B%5D=institution%3A%22UFRGS%22"},{"value":"UNESP","translated":"UNESP","count":147016,"href":"?limit=0&type=AllFields&filter%5B%5D=institution%3A%22UNESP%22"},{"value":"UFSC","translated":"UFSC","count":87315,"href":"?limit=0&type=AllFields&filter%5B%5D=institution%3A%22UFSC%22"},{"value":"UNB","translated":"UNB","count":73158,"href":"?limit=0&type=AllFields&filter%5B%5D=institution%3A%22UNB%22"},{"value":"UFC","translated":"UFC","count":68619,"href":"?limit=0&type=AllFields&filter%5B%5D=institution%3A%22UFC%22"},{"value":"UTFPR","translated":"UTFPR","count":53923,"href":"?limit=0&type=AllFields&filter%5B%5D=institution%3A%22UTFPR%22"},{"value":"UFPR","translated":"UFPR","count":52883,"href":"?limit=0&type=AllFields&filter%5B%5D=institution%3A%22UFPR%22"},{"value":"FIOCRUZ","translated":"FIOCRUZ","count":51981,"href":"?limit=0&type=AllFields&filter%5B%5D=institution%3A%22FIOCRUZ%22"},{"value":"UECE","translated":"UECE","count":45348,"href":"?limit=0&type=AllFields&filter%5B%5D=institution%3A%22UECE%22"},{"value":"UFRN","translated":"UFRN","count":34802,"href":"?limit=0&type=AllFields&filter%5B%5D=institution%3A%22UFRN%22"},{"value":"EMBRAPA","translated":"EMBRAPA","count":32188,"href":"?limit=0&type=AllFields&filter%5B%5D=institution%3A%22EMBRAPA%22"},{"value":"UFSM","translated":"UFSM","count":31533,"href":"?limit=0&type=AllFields&filter%5B%5D=institution%3A%22UFSM%22"},{"value":"UFRJ","translated":"UFRJ","count":27240,"href":"?limit=0&type=AllFields&filter%5B%5D=institution%3A%22UFRJ%22"},{"value":"UFBA","translated":"UFBA","count":26685,"href":"?limit=0&type=AllFields&filter%5B%5D=institution%3A%22UFBA%22"},{"value":"UFMG","translated":"UFMG","count":25550,"href":"?limit=0&type=AllFields&filter%5B%5D=institution%3A%22UFMG%22"},{"value":"UFPE","translated":"UFPE","count":25238,"href":"?limit=0&type=AllFields&filter%5B%5D=institution%3A%22UFPE%22"},{"value":"UFU","translated":"UFU","count":25148,"href":"?limit=0&type=AllFields&filter%5B%5D=institution%3A%22UFU%22"},{"value":"FGV","translated":"FGV","count":24827,"href":"?limit=0&type=AllFields&filter%5B%5D=institution%3A%22FGV%22"},{"value":"UFG","translated":"UFG","count":22386,"href":"?limit=0&type=AllFields&filter%5B%5D=institution%3A%22UFG%22"},{"value":"IPEN","translated":"IPEN","count":22173,"href":"?limit=0&type=AllFields&filter%5B%5D=institution%3A%22IPEN%22"},{"value":"INPA","translated":"INPA","count":21516,"href":"?limit=0&type=AllFields&filter%5B%5D=institution%3A%22INPA%22"},{"value":"UNIFESP","translated":"UNIFESP","count":21093,"href":"?limit=0&type=AllFields&filter%5B%5D=institution%3A%22UNIFESP%22"},{"value":"PUC_SP","translated":"PUC_SP","count":20944,"href":"?limit=0&type=AllFields&filter%5B%5D=institution%3A%22PUC_SP%22"},{"value":"UEL","translated":"UEL","count":16197,"href":"?limit=0&type=AllFields&filter%5B%5D=institution%3A%22UEL%22"},{"value":"PUC_RS","translated":"PUC_RS","count":15016,"href":"?limit=0&type=AllFields&filter%5B%5D=institution%3A%22PUC_RS%22"},{"value":"UERJ","translated":"UERJ","count":14752,"href":"?limit=0&type=AllFields&filter%5B%5D=institution%3A%22UERJ%22"},{"value":"UFJF","translated":"UFJF","count":14661,"href":"?limit=0&type=AllFields&filter%5B%5D=institution%3A%22UFJF%22"},{"value":"UEM","translated":"UEM","count":14110,"href":"?limit=0&type=AllFields&filter%5B%5D=institution%3A%22UEM%22"}],"dc.contributor.advisor1.fl_str_mv":[{"value":"Fialho, Francisco Antonio Pereira","translated":"Fialho, Francisco Antonio Pereira","count":409,"href":"?limit=0&type=AllFields&filter%5B%5D=dc.contributor.advisor1.fl_str_mv%3A%22Fialho%2C+Francisco+Antonio+Pereira%22"},{"value":"Orientação","translated":"Orientação","count":368,"href":"?limit=0&type=AllFields&filter%5B%5D=dc.contributor.advisor1.fl_str_mv%3A%22Orienta%C3%A7%C3%A3o%22"},{"value":"Catai, Rodrigo Eduardo","translated":"Catai, Rodrigo Eduardo","count":348,"href":"?limit=0&type=AllFields&filter%5B%5D=dc.contributor.advisor1.fl_str_mv%3A%22Catai%2C+Rodrigo+Eduardo%22"},{"value":"Bergmann, Carlos Perez","translated":"Bergmann, Carlos Perez","count":270,"href":"?limit=0&type=AllFields&filter%5B%5D=dc.contributor.advisor1.fl_str_mv%3A%22Bergmann%2C+Carlos+Perez%22"},{"value":"Marques Júnior, William Paiva","translated":"Marques Júnior, William Paiva","count":262,"href":"?limit=0&type=AllFields&filter%5B%5D=dc.contributor.advisor1.fl_str_mv%3A%22Marques+J%C3%BAnior%2C+William+Paiva%22"},{"value":"Slongo, Luiz Antonio","translated":"Slongo, Luiz Antonio","count":245,"href":"?limit=0&type=AllFields&filter%5B%5D=dc.contributor.advisor1.fl_str_mv%3A%22Slongo%2C+Luiz+Antonio%22"},{"value":"Pacheco, Vicente, 1952-","translated":"Pacheco, Vicente, 1952-","count":237,"href":"?limit=0&type=AllFields&filter%5B%5D=dc.contributor.advisor1.fl_str_mv%3A%22Pacheco%2C+Vicente%2C+1952-%22"},{"value":"Romano, Cezar Augusto","translated":"Romano, Cezar Augusto","count":234,"href":"?limit=0&type=AllFields&filter%5B%5D=dc.contributor.advisor1.fl_str_mv%3A%22Romano%2C+Cezar+Augusto%22"},{"value":"Nique, Walter Meucci","translated":"Nique, Walter Meucci","count":233,"href":"?limit=0&type=AllFields&filter%5B%5D=dc.contributor.advisor1.fl_str_mv%3A%22Nique%2C+Walter+Meucci%22"},{"value":"Simão, Marco António Alveirinho Cabrita","translated":"Simão, Marco António Alveirinho Cabrita","count":230,"href":"?limit=0&type=AllFields&filter%5B%5D=dc.contributor.advisor1.fl_str_mv%3A%22Sim%C3%A3o%2C+Marco+Ant%C3%B3nio+Alveirinho+Cabrita%22"},{"value":"Peixe, Blênio Cezar Severo, 1954-","translated":"Peixe, Blênio Cezar Severo, 1954-","count":221,"href":"?limit=0&type=AllFields&filter%5B%5D=dc.contributor.advisor1.fl_str_mv%3A%22Peixe%2C+Bl%C3%AAnio+Cezar+Severo%2C+1954-%22"},{"value":"Kloeckner, Gilberto de Oliveira","translated":"Kloeckner, Gilberto de Oliveira","count":217,"href":"?limit=0&type=AllFields&filter%5B%5D=dc.contributor.advisor1.fl_str_mv%3A%22Kloeckner%2C+Gilberto+de+Oliveira%22"},{"value":"Casagrande, Luiz Fernande","translated":"Casagrande, Luiz Fernande","count":214,"href":"?limit=0&type=AllFields&filter%5B%5D=dc.contributor.advisor1.fl_str_mv%3A%22Casagrande%2C+Luiz+Fernande%22"},{"value":"Kliemann Neto, Francisco Jose","translated":"Kliemann Neto, Francisco Jose","count":213,"href":"?limit=0&type=AllFields&filter%5B%5D=dc.contributor.advisor1.fl_str_mv%3A%22Kliemann+Neto%2C+Francisco+Jose%22"},{"value":"Beuren, Ilse Maria","translated":"Beuren, Ilse Maria","count":212,"href":"?limit=0&type=AllFields&filter%5B%5D=dc.contributor.advisor1.fl_str_mv%3A%22Beuren%2C+Ilse+Maria%22"},{"value":"Matoski, Adalberto","translated":"Matoski, Adalberto","count":202,"href":"?limit=0&type=AllFields&filter%5B%5D=dc.contributor.advisor1.fl_str_mv%3A%22Matoski%2C+Adalberto%22"},{"value":"Nascimento, Luis Felipe Machado do","translated":"Nascimento, Luis Felipe Machado do","count":200,"href":"?limit=0&type=AllFields&filter%5B%5D=dc.contributor.advisor1.fl_str_mv%3A%22Nascimento%2C+Luis+Felipe+Machado+do%22"},{"value":"Rodrigues, Marcelo","translated":"Rodrigues, Marcelo","count":198,"href":"?limit=0&type=AllFields&filter%5B%5D=dc.contributor.advisor1.fl_str_mv%3A%22Rodrigues%2C+Marcelo%22"},{"value":"Steiner Neto, Pedro José, 1954-","translated":"Steiner Neto, Pedro José, 1954-","count":198,"href":"?limit=0&type=AllFields&filter%5B%5D=dc.contributor.advisor1.fl_str_mv%3A%22Steiner+Neto%2C+Pedro+Jos%C3%A9%2C+1954-%22"},{"value":"Urbanetz Junior, Jair","translated":"Urbanetz Junior, Jair","count":195,"href":"?limit=0&type=AllFields&filter%5B%5D=dc.contributor.advisor1.fl_str_mv%3A%22Urbanetz+Junior%2C+Jair%22"},{"value":"Francisco, Antonio Carlos de","translated":"Francisco, Antonio Carlos de","count":194,"href":"?limit=0&type=AllFields&filter%5B%5D=dc.contributor.advisor1.fl_str_mv%3A%22Francisco%2C+Antonio+Carlos+de%22"},{"value":"Salgado, José Ronaldo Aguiar","translated":"Salgado, José Ronaldo Aguiar","count":193,"href":"?limit=0&type=AllFields&filter%5B%5D=dc.contributor.advisor1.fl_str_mv%3A%22Salgado%2C+Jos%C3%A9+Ronaldo+Aguiar%22"},{"value":"Borsoi, Beatriz Terezinha","translated":"Borsoi, Beatriz Terezinha","count":190,"href":"?limit=0&type=AllFields&filter%5B%5D=dc.contributor.advisor1.fl_str_mv%3A%22Borsoi%2C+Beatriz+Terezinha%22"},{"value":"Ribeiro, Jose Luis Duarte","translated":"Ribeiro, Jose Luis Duarte","count":189,"href":"?limit=0&type=AllFields&filter%5B%5D=dc.contributor.advisor1.fl_str_mv%3A%22Ribeiro%2C+Jose+Luis+Duarte%22"},{"value":"Martins, José Carlos Tudela","translated":"Martins, José Carlos Tudela","count":186,"href":"?limit=0&type=AllFields&filter%5B%5D=dc.contributor.advisor1.fl_str_mv%3A%22Martins%2C+Jos%C3%A9+Carlos+Tudela%22"},{"value":"Sousa, Miguel Castelo Branco Craveiro de","translated":"Sousa, Miguel Castelo Branco Craveiro de","count":183,"href":"?limit=0&type=AllFields&filter%5B%5D=dc.contributor.advisor1.fl_str_mv%3A%22Sousa%2C+Miguel+Castelo+Branco+Craveiro+de%22"},{"value":"Strohaecker, Telmo Roberto","translated":"Strohaecker, Telmo Roberto","count":181,"href":"?limit=0&type=AllFields&filter%5B%5D=dc.contributor.advisor1.fl_str_mv%3A%22Strohaecker%2C+Telmo+Roberto%22"},{"value":"Vale, Vera Maria Silvério do, 1961-","translated":"Vale, Vera Maria Silvério do, 1961-","count":178,"href":"?limit=0&type=AllFields&filter%5B%5D=dc.contributor.advisor1.fl_str_mv%3A%22Vale%2C+Vera+Maria+Silv%C3%A9rio+do%2C+1961-%22"},{"value":"Silva, Germano Marques da","translated":"Silva, Germano Marques da","count":177,"href":"?limit=0&type=AllFields&filter%5B%5D=dc.contributor.advisor1.fl_str_mv%3A%22Silva%2C+Germano+Marques+da%22"},{"value":"Schaeffer, Lirio","translated":"Schaeffer, Lirio","count":176,"href":"?limit=0&type=AllFields&filter%5B%5D=dc.contributor.advisor1.fl_str_mv%3A%22Schaeffer%2C+Lirio%22"}]},"status":["OK"]}
